aliyunsdklinkvisual/__init__.py
aliyunsdklinkvisual/endpoint.py
aliyunsdklinkvisual/request/__init__.py
aliyunsdklinkvisual/request/v20180120/AddEventRecordPlanDeviceRequest.py
aliyunsdklinkvisual/request/v20180120/AddFaceDeviceGroupRequest.py
aliyunsdklinkvisual/request/v20180120/AddFaceDeviceToDeviceGroupRequest.py
aliyunsdklinkvisual/request/v20180120/AddFaceUserGroupAndDeviceGroupRelationRequest.py
aliyunsdklinkvisual/request/v20180120/AddFaceUserGroupRequest.py
aliyunsdklinkvisual/request/v20180120/AddFaceUserPictureRequest.py
aliyunsdklinkvisual/request/v20180120/AddFaceUserRequest.py
aliyunsdklinkvisual/request/v20180120/AddFaceUserToUserGroupRequest.py
aliyunsdklinkvisual/request/v20180120/AddRecordPlanDeviceRequest.py
aliyunsdklinkvisual/request/v20180120/BindPictureSearchAppWithDevicesRequest.py
aliyunsdklinkvisual/request/v20180120/CheckFaceUserDoExistOnDeviceRequest.py
aliyunsdklinkvisual/request/v20180120/ClearFaceDeviceDBRequest.py
aliyunsdklinkvisual/request/v20180120/CreateEventRecordPlanRequest.py
aliyunsdklinkvisual/request/v20180120/CreateLocalFileUploadJobRequest.py
aliyunsdklinkvisual/request/v20180120/CreatePictureSearchAppRequest.py
aliyunsdklinkvisual/request/v20180120/CreatePictureSearchJobRequest.py
aliyunsdklinkvisual/request/v20180120/CreateRecordPlanRequest.py
aliyunsdklinkvisual/request/v20180120/CreateTimeTemplateRequest.py
aliyunsdklinkvisual/request/v20180120/DeleteEventRecordPlanDeviceRequest.py
aliyunsdklinkvisual/request/v20180120/DeleteEventRecordPlanRequest.py
aliyunsdklinkvisual/request/v20180120/DeleteFaceDeviceGroupRequest.py
aliyunsdklinkvisual/request/v20180120/DeleteFaceUserGroupAndDeviceGroupRelationRequest.py
aliyunsdklinkvisual/request/v20180120/DeleteFaceUserGroupRequest.py
aliyunsdklinkvisual/request/v20180120/DeleteFaceUserPictureRequest.py
aliyunsdklinkvisual/request/v20180120/DeleteFaceUserRequest.py
aliyunsdklinkvisual/request/v20180120/DeleteLocalFileUploadJobRequest.py
aliyun_python_sdk_linkvisual-1.5.8.dist-info/LICENSE
aliyun_python_sdk_linkvisual-1.5.8.dist-info/METADATA
aliyun_python_sdk_linkvisual-1.5.8.dist-info/WHEEL
aliyun_python_sdk_linkvisual-1.5.8.dist-info/top_level.txt
aliyun_python_sdk_linkvisual-1.5.8.dist-info/RECORD
